{
    "application": {
        "id": "",
        "title": "com.so.SalesOrders",
        "description": "Manage SalesOrders",
        "type": "SAP_UI5_Component",
        "componentUrl": "/",
        "appUrl": "#SalesOrders-Display",
        "navigationComponentName": "com.so.SalesOrders",
        "intentSemanticObject": "SalesOrders",
        "intentAction": "Display",
        "html5ApplicationName": "managesalesorders",
        "HCPParentApplicationName": ""
    },
    "assignment": {
        "groups": [
            "07aa98b2-c239-4899-8b3f-29da426982a4-1590036552659"
        ],
        "contentPackages": [
            "136068f7-cfa4-415b-8083-18f38d228f05-1590036478893"
        ],
        "categories": []
    },
    "tile": {
        "type": "StaticTile",
        "title": "SalesOrders",
        "subtitle": "SalesOders ES5",
        "searchKeywords": "SalesOrders,SalesOders ES5",
        "displayIconUrl": "sap-icon://my-sales-order",
        "displayInfoText": "",
        "size": "1x1",
        "serviceURL": "",
        "refreshInterval": ""
    }
}